[
	{
		"key": "sb",
		"value": "THzFYL2kJRsaIDUcZJ1ikNrW",
		"domain": "facebook.com",
		"path": "/",
		"hostOnly": false,
		"creation": "2021-07-12T13:36:07.093Z",
		"lastAccessed": "2021-07-12T13:36:10.006Z"
	},
	{
		"key": "locale",
		"value": "vi_VN",
		"domain": "facebook.com",
		"path": "/",
		"hostOnly": false,
		"creation": "2021-07-12T13:36:07.113Z",
		"lastAccessed": "2021-07-12T13:36:10.006Z"
	},
	{
		"key": "wd",
		"value": "1876x1001",
		"domain": "facebook.com",
		"path": "/",
		"hostOnly": false,
		"creation": "2021-07-12T13:36:07.115Z",
		"lastAccessed": "2021-07-12T13:36:10.006Z"
	},
	{
		"key": "c_user",
		"value": "100070165226428",
		"domain": "facebook.com",
		"path": "/",
		"hostOnly": false,
		"creation": "2021-07-12T13:36:07.117Z",
		"lastAccessed": "2021-07-12T13:36:10.006Z"
	},
	{
		"key": "spin",
		"value": "r.1004100858_b.trunk_t.1626095649_s.1_v.2_",
		"domain": "facebook.com",
		"path": "/",
		"hostOnly": false,
		"creation": "2021-07-12T13:36:07.119Z",
		"lastAccessed": "2021-07-12T13:36:10.006Z"
	},
	{
		"key": "datr",
		"value": "HEDsYOxhEAwU0jWkn9Mecz6U",
		"domain": "facebook.com",
		"path": "/",
		"hostOnly": false,
		"creation": "2021-07-12T13:36:07.120Z",
		"lastAccessed": "2021-07-12T13:36:10.006Z"
	},
	{
		"key": "xs",
		"value": "42%3AA07fEPwtloxf7w%3A2%3A1626095639%3A-1%3A-1%3A%3AAcUFaXgN8g5dMrEZMf4dEd14qnvXMp8KzslD4og5NQ",
		"domain": "facebook.com",
		"path": "/",
		"hostOnly": false,
		"creation": "2021-07-12T13:36:07.121Z",
		"lastAccessed": "2021-07-12T13:36:10.006Z"
	},
	{
		"key": "fr",
		"value": "1rY59mQeWqZ2xtUky.AWWwjjoOmZ2Tyo9fFIXynXYQZzI.Bg7ER0.op.AAA.0.0.Bg7ER0.AWXxZCHhp-I",
		"domain": "facebook.com",
		"path": "/",
		"hostOnly": false,
		"creation": "2021-07-12T13:36:07.121Z",
		"lastAccessed": "2021-07-12T13:36:10.006Z"
	},
	{
		"key": "sb",
		"value": "THzFYL2kJRsaIDUcZJ1ikNrW",
		"domain": "facebook.com",
		"path": "/",
		"hostOnly": false,
		"creation": "2021-07-12T13:36:07.093Z",
		"lastAccessed": "2021-07-12T13:36:10.006Z"
	},
	{
		"key": "locale",
		"value": "vi_VN",
		"domain": "facebook.com",
		"path": "/",
		"hostOnly": false,
		"creation": "2021-07-12T13:36:07.113Z",
		"lastAccessed": "2021-07-12T13:36:10.006Z"
	},
	{
		"key": "wd",
		"value": "1876x1001",
		"domain": "facebook.com",
		"path": "/",
		"hostOnly": false,
		"creation": "2021-07-12T13:36:07.115Z",
		"lastAccessed": "2021-07-12T13:36:10.006Z"
	},
	{
		"key": "c_user",
		"value": "100070165226428",
		"domain": "facebook.com",
		"path": "/",
		"hostOnly": false,
		"creation": "2021-07-12T13:36:07.117Z",
		"lastAccessed": "2021-07-12T13:36:10.006Z"
	},
	{
		"key": "spin",
		"value": "r.1004100858_b.trunk_t.1626095649_s.1_v.2_",
		"domain": "facebook.com",
		"path": "/",
		"hostOnly": false,
		"creation": "2021-07-12T13:36:07.119Z",
		"lastAccessed": "2021-07-12T13:36:10.006Z"
	},
	{
		"key": "datr",
		"value": "HEDsYOxhEAwU0jWkn9Mecz6U",
		"domain": "facebook.com",
		"path": "/",
		"hostOnly": false,
		"creation": "2021-07-12T13:36:07.120Z",
		"lastAccessed": "2021-07-12T13:36:10.006Z"
	},
	{
		"key": "xs",
		"value": "42%3AA07fEPwtloxf7w%3A2%3A1626095639%3A-1%3A-1%3A%3AAcUFaXgN8g5dMrEZMf4dEd14qnvXMp8KzslD4og5NQ",
		"domain": "facebook.com",
		"path": "/",
		"hostOnly": false,
		"creation": "2021-07-12T13:36:07.121Z",
		"lastAccessed": "2021-07-12T13:36:10.006Z"
	},
	{
		"key": "fr",
		"value": "1rY59mQeWqZ2xtUky.AWWwjjoOmZ2Tyo9fFIXynXYQZzI.Bg7ER0.op.AAA.0.0.Bg7ER0.AWXxZCHhp-I",
		"domain": "facebook.com",
		"path": "/",
		"hostOnly": false,
		"creation": "2021-07-12T13:36:07.121Z",
		"lastAccessed": "2021-07-12T13:36:10.006Z"
	}
]